BFQ/BFQ.cpython-37m-x86_64-linux-gnu.so
BFQ/__init__.py
BFQ-1.3.0.7.dist-info/LICENSE
BFQ-1.3.0.7.dist-info/METADATA
BFQ-1.3.0.7.dist-info/WHEEL
BFQ-1.3.0.7.dist-info/top_level.txt
BFQ-1.3.0.7.dist-info/RECORD
