Metadata-Version: 2.1
Name: BFQ
Version: 1.3.0.7
Summary: 博采众长的人脸质量评价库
Home-page: https://zhengtq.github.io/
Author: Billy
Author-email: ztqstd@163.com
License: MIT
Platform: UNKNOWN
Requires-Python: >=3.7.0
Requires-Dist: numpy
